MANIFEST.in
dedepuyer.py
setup.py
debin/dedepuyers
dedepuyer.egg-info/PKG-INFO
dedepuyer.egg-info/SOURCES.txt
dedepuyer.egg-info/dependency_links.txt
dedepuyer.egg-info/entry_points.txt
dedepuyer.egg-info/top_level.txt