Metadata-Version: 1.1
Name: dedepuyer
Version: 0.2.5
Summary: A project to find git information.
Home-page: http://gitlab.h-seo.com/adhitj/dedepuyer
Author: AdhiTj
Author-email: adhitjatur@gmail.com
License: GPLv3+
Platform: UNKNOWN
Classifier: Development Status :: 3 - Alpha
Classifier: Intended Audience :: Developers
Classifier: License :: OSI Approved :: GNU General Public License v3 or later (GPLv3+)
Classifier: Programming Language :: Python :: 2.7
